jwt_token_x21124213/__init__.py
jwt_token_x21124213/token_prop.py
jwt_token_x21124213-0.0.6.dist-info/METADATA
jwt_token_x21124213-0.0.6.dist-info/WHEEL
jwt_token_x21124213-0.0.6.dist-info/licenses/LICENSE
jwt_token_x21124213-0.0.6.dist-info/RECORD
